beard/__init__.py
beard/clustering/__init__.py
beard/clustering/blocking.py
beard/clustering/blocking_funcs.py
beard/clustering/wrappers.py
beard/ext/__init__.py
beard/ext/metaphone.py
beard/metrics/__init__.py
beard/metrics/clustering.py
beard/metrics/text.py
beard/similarity/__init__.py
beard/similarity/pairs.py
beard/utils/__init__.py
beard/utils/misc.py
beard/utils/names.py
beard/utils/strings.py
beard/utils/transformers.py
beard-0.2.1.dist-info/AUTHORS.rst
beard-0.2.1.dist-info/LICENSE.rst
beard-0.2.1.dist-info/METADATA
beard-0.2.1.dist-info/WHEEL
beard-0.2.1.dist-info/top_level.txt
beard-0.2.1.dist-info/RECORD
